socialgene/__init__.py
socialgene/common_parameters.env
socialgene/config.py
socialgene/addons/__init__.py
socialgene/addons/antismash/__init__.py
socialgene/addons/antismash/nr.py
socialgene/addons/chebi/__init__.py
socialgene/addons/chebi/nr.py
socialgene/addons/chembl/__init__.py
socialgene/addons/chembl/nr.py
socialgene/addons/chemistry/__init__.py
socialgene/addons/chemistry/cli_similarity.py
socialgene/addons/chemistry/nr.py
socialgene/addons/chemistry/substruct.py
socialgene/addons/classyfire/__init__.py
socialgene/addons/classyfire/cli.py
socialgene/addons/classyfire/nr.py
socialgene/addons/classyfire/parse.py
socialgene/addons/culture_collections/__init__.py
socialgene/addons/culture_collections/nr.py
socialgene/addons/gene_cluster/__init__.py
socialgene/addons/gene_cluster/nr.py
socialgene/addons/gnps_library/__init__.py
socialgene/addons/gnps_library/nr.py
socialgene/addons/gnps_library/parse.py
socialgene/addons/gnps_networking/__init__.py
socialgene/addons/gnps_networking/cli.py
socialgene/addons/gnps_networking/nr.py
socialgene/addons/gnps_networking/parse.py
socialgene/addons/mibig/__init__.py
socialgene/addons/mibig/link_cli.py
socialgene/addons/mibig/nr.py
socialgene/addons/npatlas/__init__.py
socialgene/addons/npatlas/cli.py
socialgene/addons/npatlas/nr.py
socialgene/addons/npatlas/parse.py
socialgene/addons/npclassifier/__init__.py
socialgene/addons/npclassifier/nr.py
socialgene/addons/npmrd/__init__.py
socialgene/addons/npmrd/nr.py
socialgene/addons/publication/__init__.py
socialgene/addons/publication/nr.py
socialgene/base/__init__.py
socialgene/base/chem.py
socialgene/base/compare_protein.py
socialgene/base/locus_metadata.py
socialgene/base/molbio.py
socialgene/base/socialgene.py
socialgene/cli/__init__.py
socialgene/cli/__main__.py
socialgene/cli/external_mods/__init__.py
socialgene/cli/external_mods/gnps.py
socialgene/cli/neo4j/__init__.py
socialgene/cli/neo4j/indices.py
socialgene/cli/neo4j/massage.py
socialgene/cli/nextflow/__init__.py
socialgene-2.0.1.dist-info/licenses/LICENSE.md
socialgene-2.0.1.dist-info/METADATA
socialgene-2.0.1.dist-info/WHEEL
socialgene-2.0.1.dist-info/entry_points.txt
socialgene-2.0.1.dist-info/top_level.txt
socialgene-2.0.1.dist-info/RECORD
