Metadata-Version: 2.4
Name: socialgene
Version: 2.0.1
Summary: Creating and interacting with graph databases of protein domains and their genome coordinates
Author-email: "Chase M. Clark" <chasingmicrobes@gmail.com>
License: MIT
Project-URL: repository, https://github.com/socialgene/sgpy
Project-URL: homepage, https://socialgene.github.io
Classifier: Development Status :: 3 - Alpha
Classifier: Intended Audience :: Science/Research
Classifier: License :: OSI Approved :: MIT License
Classifier: Operating System :: Unix
Classifier: Operating System :: POSIX
Classifier: Operating System :: Microsoft :: Windows
Classifier: Operating System :: OS Independent
Classifier: Topic :: Software Development :: Libraries :: Python Modules
Classifier: License :: OSI Approved :: MIT License
Classifier: Programming Language :: Python :: 3
Requires-Python: >=3.12
License-File: LICENSE.md
Requires-Dist: rdkit==2025.3.3
Requires-Dist: pandas>=2
Requires-Dist: numpy>=2
Requires-Dist: neo4j>=5.22.0
Requires-Dist: biopython>=1.84
Requires-Dist: textdistance>=4.6.3
Requires-Dist: rich>=13.7
Requires-Dist: requests>=2.32
Provides-Extra: chem
Requires-Dist: rdkit; extra == "chem"
Provides-Extra: ci
Requires-Dist: pytest-cov; extra == "ci"
Provides-Extra: cd
Requires-Dist: twine; extra == "cd"
Dynamic: license-file
